pyqtcs/BOLL.py
pyqtcs/MA.py
pyqtcs/__init__.py
pyqtcs/qtclass.py
pyqtcs/test_index.py
pyqtcs/wewe.py
pyqtcs/formula_analysis/__init__.py
pyqtcs/formula_analysis/formula_analysis.py
pyqtcs/func/__init__.py
pyqtcs/func/func.py
pyqtcs/func/split_index.py
pyqtcs-1.1.1.dist-info/METADATA
pyqtcs-1.1.1.dist-info/WHEEL
pyqtcs-1.1.1.dist-info/top_level.txt
pyqtcs-1.1.1.dist-info/RECORD
