Metadata-Version: 2.1
Name: pyqtcs
Version: 1.1.1
Summary: Python wrapper for qtcs: natural language processing
Home-page: https://pypi.org
Author: chenghaiyuan
Author-email: 334180587@1qq.com
License: UNKNOWN
Platform: UNKNOWN
Classifier: Programming Language :: Python :: 3
Classifier: License :: OSI Approved :: MIT License
Requires-Dist: numpy
Requires-Dist: ta-lib
